appeears/__init__.py
appeears/appeears.py
appeears-0.0.3.dist-info/LICENSE
appeears-0.0.3.dist-info/METADATA
appeears-0.0.3.dist-info/WHEEL
appeears-0.0.3.dist-info/entry_points.txt
appeears-0.0.3.dist-info/top_level.txt
appeears-0.0.3.dist-info/RECORD
