Metadata-Version: 2.1
Name: appeears
Version: 0.0.3
Summary: Simple CLI for NASA AppEEARS API
Home-page: https://github.com/samapriya/appeears
Author: Samapriya Roy
Author-email: samapriya.roy@gmail.com
License: Apache 2.0
Platform: UNKNOWN
Classifier: Intended Audience :: Developers
Classifier: Intended Audience :: Science/Research
Classifier: Natural Language :: English
Classifier: License :: OSI Approved :: Apache Software License
Classifier: Programming Language :: Python :: 3.6
Classifier: Programming Language :: Python :: 3.7
Classifier: Operating System :: OS Independent
Classifier: Topic :: Scientific/Engineering :: GIS
Requires-Dist: tqdm (>=4.56.0)
Requires-Dist: requests (>=2.28.1)
Requires-Dist: natsort (>=8.1.0)
Requires-Dist: beautifulsoup4 (>=4.11.1)
Requires-Dist: tabulate (>=0.8.9)
Requires-Dist: PyGeoj (==1.0.0)
